recommender/rec.py
recommender/data/movies.txt
recommender_testing11-0.5.dist-info/METADATA
recommender_testing11-0.5.dist-info/WHEEL
recommender_testing11-0.5.dist-info/top_level.txt
recommender_testing11-0.5.dist-info/RECORD
